setup.cfg
setup.py
bin/trollcast_client
bin/trollcast_server
trollcast/__init__.py
trollcast/client.py
trollcast/get_sar.py
trollcast/gui.py
trollcast/oldserver.py
trollcast/schedules.py
trollcast/server.py
trollcast/test_socketstreamer.py
trollcast/version.py
trollcast.egg-info/PKG-INFO
trollcast.egg-info/SOURCES.txt
trollcast.egg-info/dependency_links.txt
trollcast.egg-info/not-zip-safe
trollcast.egg-info/requires.txt
trollcast.egg-info/top_level.txt