Metadata-Version: 1.1
Name: trollcast
Version: 1.0.1
Summary: Weather satellite data exchange tool
Home-page: UNKNOWN
Author: The pytroll team
Author-email: martin.raspaud@smhi.se
License: GPLv3
Platform: UNKNOWN
Classifier: Development Status :: 5 - Production/Stable
Classifier: License :: OSI Approved :: GNU General Public License v3 (GPLv3)
Classifier: Programming Language :: Python
Classifier: Operating System :: OS Independent
Classifier: Intended Audience :: Science/Research
Classifier: Topic :: Scientific/Engineering
Classifier: Topic :: Communications
